{"FloorClipPlane": {"Item2": 0, "Item3": 0, "Item1": 0, "Item4": 0}, "TimeStamp": 1982490, "FrameNumber": 54204, "Skeletons": [{"Position": {"Y": 0.0355934, "X": 0.0356097631, "Z": 2.16327524}, "TrackingState": 2, "TrackingID": 7523, "Joints": [{"Position": {"Y": 0.134457529, "X": 0.0565907136, "Z": 2.29928565}, "TrackingState": 2, "JointType": "HipCenter"}, {"Position": {"Y": 0.197373092, "X": 0.028856948, "Z": 2.330194}, "TrackingState": 2, "JointType": "Spine"}, {"Position": {"Y": 0.5557959, "X": 0.006685258, "Z": 2.38118148}, "TrackingState": 2, "JointType": "ShoulderCenter"}, {"Position": {"Y": 0.724397838, "X": -0.04166203, "Z": 2.4034822}, "TrackingState": 2, "JointType": "Head"}, {"Position": {"Y": 0.410292149, "X": -0.00247289916, "Z": 2.29802632}, "TrackingState": 1, "JointType": "ShoulderLeft"}, {"Position": {"Y": 0.3942142, "X": -0.0251915548, "Z": 2.05934072}, "TrackingState": 1, "JointType": "ElbowLeft"}, {"Position": {"Y": 0.359505534, "X": -0.06059417, "Z": 1.83360863}, "TrackingState": 2, "JointType": "WristLeft"}, {"Position": {"Y": 0.3633808, "X": -0.06876014, "Z": 1.63379812}, "TrackingState": 2, "JointType": "HandLeft"}, {"Position": {"Y": 0.471736372, "X": 0.0756545961, "Z": 2.39405131}, "TrackingState": 2, "JointType": "ShoulderRight"}, {"Position": {"Y": 0.3907138, "X": 0.2553305, "Z": 2.52539325}, "TrackingState": 2, "JointType": "ElbowRight"}, {"Position": {"Y": 0.3555837, "X": 0.45569092, "Z": 2.65951467}, "TrackingState": 2, "JointType": "WristRight"}, {"Position": {"Y": 0.3486538, "X": 0.5240624, "Z": 2.71365714}, "TrackingState": 2, "JointType": "HandRight"}, {"Position": {"Y": 0.10333246, "X": 0.0377271, "Z": 2.29488873}, "TrackingState": 2, "JointType": "HipLeft"}, {"Position": {"Y": -0.102180474, "X": 0.160015792, "Z": 1.88771081}, "TrackingState": 2, "JointType": "KneeLeft"}, {"Position": {"Y": -0.285054982, "X": -0.02673395, "Z": 2.145038}, "TrackingState": 2, "JointType": "AnkleLeft"}, {"Position": {"Y": -0.3318883, "X": -0.07032338, "Z": 2.213487}, "TrackingState": 2, "JointType": "FootLeft"}, {"Position": {"Y": 0.120609879, "X": 0.08152432, "Z": 2.29532361}, "TrackingState": 2, "JointType": "HipRight"}, {"Position": {"Y": -0.268808365, "X": 0.0784160346, "Z": 2.35941958}, "TrackingState": 2, "JointType": "KneeRight"}, {"Position": {"Y": -0.540871263, "X": 0.004703246, "Z": 2.30898547}, "TrackingState": 1, "JointType": "AnkleRight"}, {"Position": {"Y": -0.471076727, "X": -0.0334204622, "Z": 2.35262847}, "TrackingState": 2, "JointType": "FootRight"}]}]}